gdnet/__init__.py
gdnet/core.py
gdnet/gpu.py
gdnet/activations/Dropout.py
gdnet/activations/LeakyRELU.py
gdnet/activations/Linear.py
gdnet/activations/RELU.py
gdnet/activations/Sigmoid.py
gdnet/activations/Softmax.py
gdnet/activations/__init__.py
gdnet/activations/base.py
gdnet/layers/Conv2DLayer.py
gdnet/layers/DebugShape.py
gdnet/layers/DenseLayer.py
gdnet/layers/DotProductAttentionLayer.py
gdnet/layers/DropoutLayer.py
gdnet/layers/EmbeddingLayer.py
gdnet/layers/Flatten.py
gdnet/layers/MaxPool2dLayer.py
gdnet/layers/MultiHeadAttentionLayer.py
gdnet/layers/PositionalEmbeddingLayer.py
gdnet/layers/TransformerBlock.py
gdnet/layers/TransformerFeedForwardLayer.py
gdnet/layers/__init__.py
gdnet/layers/base.py
gdnet/lossfunctions/BinaryCrossEntropy.py
gdnet/lossfunctions/CrossEntropy.py
gdnet/lossfunctions/FocalLoss.py
gdnet/lossfunctions/HuberLoss.py
gdnet/lossfunctions/KLDivergence.py
gdnet/lossfunctions/MAE.py
gdnet/lossfunctions/MSE.py
gdnet/lossfunctions/__init__.py
gdnet/lossfunctions/base.py
gdnet/optimizers/ConvOptimization.py
gdnet/optimizers/adam.py
gdnet/tranformers/TransformerBlock.py
gdnet/tranformers/TransformerFeedForwardLayer.py
gdnet/tranformers/__init__.py
gdnet/utils/AugmentImage.py
gdnet/utils/DebugLogger.py
gdnet/utils/TextManager.py
gdnet/utils/__init__.py
gdnet/utils/regularization.py
gdnet-0.2.dist-info/licenses/LICENSE
gdnet-0.2.dist-info/METADATA
gdnet-0.2.dist-info/WHEEL
gdnet-0.2.dist-info/top_level.txt
gdnet-0.2.dist-info/RECORD
