Metadata-Version: 2.4
Name: gdnet
Version: 0.2
Summary: A lightweight neural network framework
Author: Ghua8088
License: MIT
Classifier: Programming Language :: Python :: 3
Classifier: License :: OSI Approved :: MIT License
Requires-Python: >=3.7
License-File: LICENSE
Requires-Dist: numpy
Requires-Dist: cupy-cuda12x
Requires-Dist: scikit-learn
Requires-Dist: nltk
Requires-Dist: scipy
Requires-Dist: numba
Requires-Dist: torch
Dynamic: license-file
